alibabacloud_iqs20241111/__init__.py
alibabacloud_iqs20241111/client.py
alibabacloud_iqs20241111/models/__init__.py
alibabacloud_iqs20241111/models/_ai_search_request.py
alibabacloud_iqs20241111/models/_ai_search_response.py
alibabacloud_iqs20241111/models/_ai_search_response_body.py
alibabacloud_iqs20241111/models/_aisearch_query.py
alibabacloud_iqs20241111/models/_generic_advanced_search_request.py
alibabacloud_iqs20241111/models/_generic_advanced_search_response.py
alibabacloud_iqs20241111/models/_generic_search_request.py
alibabacloud_iqs20241111/models/_generic_search_response.py
alibabacloud_iqs20241111/models/_generic_search_result.py
alibabacloud_iqs20241111/models/_generic_search_shrink_request.py
alibabacloud_iqs20241111/models/_get_iqs_usage_request.py
alibabacloud_iqs20241111/models/_get_iqs_usage_response.py
alibabacloud_iqs20241111/models/_get_iqs_usage_result.py
alibabacloud_iqs20241111/models/_global_page_item.py
alibabacloud_iqs20241111/models/_global_query_context.py
alibabacloud_iqs20241111/models/_global_scene_item.py
alibabacloud_iqs20241111/models/_global_search_information.py
alibabacloud_iqs20241111/models/_global_search_request.py
alibabacloud_iqs20241111/models/_global_search_response.py
alibabacloud_iqs20241111/models/_global_search_result.py
alibabacloud_iqs20241111/models/_include_image.py
alibabacloud_iqs20241111/models/_location_info.py
alibabacloud_iqs20241111/models/_query_context.py
alibabacloud_iqs20241111/models/_read_page_basic_request.py
alibabacloud_iqs20241111/models/_read_page_basic_response.py
alibabacloud_iqs20241111/models/_read_page_basic_response_body.py
alibabacloud_iqs20241111/models/_read_page_body.py
alibabacloud_iqs20241111/models/_read_page_item.py
alibabacloud_iqs20241111/models/_read_page_scrape_body.py
alibabacloud_iqs20241111/models/_read_page_scrape_request.py
alibabacloud_iqs20241111/models/_read_page_scrape_response.py
alibabacloud_iqs20241111/models/_read_page_scrape_response_body.py
alibabacloud_iqs20241111-1.6.4.dist-info/LICENSE
alibabacloud_iqs20241111-1.6.4.dist-info/METADATA
alibabacloud_iqs20241111-1.6.4.dist-info/WHEEL
alibabacloud_iqs20241111-1.6.4.dist-info/top_level.txt
alibabacloud_iqs20241111-1.6.4.dist-info/RECORD
